[{"marker":[0],"components":[{"x":25,"y":20}]},{"marker":[1],"components":[{"x":25,"y":14}]},{"marker":[2],"components":[{"x":24,"y":30}]},{"marker":[3],"components":[{"x":37,"y":20}]},{"marker":[4],"components":[{"x":18,"y":14}]},{"marker":[5],"components":[{"x":11,"y":20}]},{"marker":[6],"components":[{"x":36,"y":19}]},{"marker":[7],"components":[{"x":13,"y":19}]},{"marker":[8],"components":[{"x":32,"y":20}]},{"marker":[9],"components":[null]},{"marker":[10],"components":[{"x":15,"y":19}]},{"marker":[11],"components":[{"x":31,"y":20}]},{"marker":[12],"components":[{"x":25,"y":9}]},{"marker":[13],"components":[{"x":25,"y":26}]},{"marker":[14],"components":[{"x":34,"y":19}]},{"marker":[15],"components":[{"x":18,"y":20}]},{"marker":[16],"components":[null]},{"marker":[17],"components":[{"x":19,"y":19}]},{"marker":[18],"components":[{"x":20,"y":20}]},{"marker":[19],"components":[null]},{"marker":[20],"components":[null]},{"marker":[21],"components":[null]},{"marker":[22],"components":[null]},{"marker":[23],"components":[null]},{"marker":[24],"components":[null]},{"marker":[25],"components":[null]},{"marker":[26],"components":[null]},{"marker":[27],"components":[null]},{"marker":[28],"components":[null]},{"marker":[29],"components":[null]},{"marker":[30],"components":[null]},{"marker":[31],"components":[null]},{"marker":[32],"components":[null]},{"marker":[33],"components":[null]},{"marker":[34],"components":[null]},{"marker":[35],"components":[{"x":29,"y":13}]},{"marker":[36],"components":[{"x":27,"y":19}]},{"marker":[37],"components":[{"x":25,"y":19}]},{"marker":[38],"components":[{"x":24,"y":21}]},{"marker":[39],"components":[{"x":24,"y":23}]},{"marker":[40],"components":[{"x":26,"y":20}]},{"marker":[41],"components":[{"x":24,"y":20}]},{"marker":[42],"components":[{"x":27,"y":20}]},{"marker":[43],"components":[{"x":25,"y":19}]},{"marker":[44],"components":[{"x":26,"y":21}]},{"marker":[45],"components":[{"x":17,"y":14}]},{"marker":[46],"components":[{"x":28,"y":30}]},{"marker":[47],"components":[{"x":31,"y":22}]},{"marker":[48],"components":[{"x":17,"y":15}]},{"marker":[49],"components":[{"x":16,"y":22}]},{"marker":[50],"components":[{"x":31,"y":25}]},{"marker":[51],"components":[{"x":34,"y":24}]},{"marker":[52],"components":[null]}][{"marker":[0],"components":[null]},{"marker":[1],"components":[null]},{"marker":[2],"components":[null]},{"marker":[3],"components":[null]},{"marker":[4],"components":[null]},{"marker":[5],"components":[null]},{"marker":[6],"components":[null]},{"marker":[7],"components":[null]},{"marker":[8],"components":[null]},{"marker":[9],"components":[null]},{"marker":[10],"components":[null]},{"marker":[11],"components":[null]},{"marker":[12],"components":[null]},{"marker":[13],"components":[null]},{"marker":[14],"components":[null]},{"marker":[15],"components":[null]},{"marker":[16],"components":[null]},{"marker":[17],"components":[null]},{"marker":[18],"components":[null]},{"marker":[19],"components":[null]},{"marker":[20],"components":[null]},{"marker":[21],"components":[null]},{"marker":[22],"components":[null]},{"marker":[23],"components":[null]},{"marker":[24],"components":[null]},{"marker":[25],"components":[null]},{"marker":[26],"components":[null]},{"marker":[27],"components":[null]},{"marker":[28],"components":[null]},{"marker":[29],"components":[null]},{"marker":[30],"components":[null]},{"marker":[31],"components":[null]},{"marker":[32],"components":[null]},{"marker":[33],"components":[null]},{"marker":[34],"components":[null]},{"marker":[35],"components":[null]},{"marker":[36],"components":[null]},{"marker":[37],"components":[null]},{"marker":[38],"components":[null]},{"marker":[39],"components":[null]},{"marker":[40],"components":[null]},{"marker":[41],"components":[null]},{"marker":[42],"components":[null]},{"marker":[43],"components":[null]},{"marker":[44],"components":[null]},{"marker":[45],"components":[null]},{"marker":[46],"components":[null]},{"marker":[47],"components":[null]},{"marker":[48],"components":[null]},{"marker":[49],"components":[null]},{"marker":[50],"components":[null]},{"marker":[51],"components":[null]},{"marker":[52],"components":[null]}][{"marker":[0],"components":[{"glyph":2,"fg":{"r":1.0,"g":0.19607843,"b":0.0},"bg":{"r":0.0,"g":0.0,"b":0.0},"render_order":0}]},{"marker":[1],"components":[{"glyph":234,"fg":{"r":0.08235294,"g":0.9647059,"b":0.43529412},"bg":{"r":0.0,"g":0.0,"b":0.0},"render_order":1}]},{"marker":[2],"components":[{"glyph":234,"fg":{"r":0.08235294,"g":0.9647059,"b":0.43529412},"bg":{"r":0.0,"g":0.0,"b":0.0},"render_order":1}]},{"marker":[3],"components":[{"glyph":234,"fg":{"r":0.08235294,"g":0.9647059,"b":0.43529412},"bg":{"r":0.0,"g":0.0,"b":0.0},"render_order":1}]},{"marker":[4],"components":[{"glyph":234,"fg":{"r":0.08235294,"g":0.9647059,"b":0.43529412},"bg":{"r":0.0,"g":0.0,"b":0.0},"render_order":1}]},{"marker":[5],"components":[{"glyph":234,"fg":{"r":0.08235294,"g":0.9647059,"b":0.43529412},"bg":{"r":0.0,"g":0.0,"b":0.0},"render_order":1}]},{"marker":[6],"components":[{"glyph":234,"fg":{"r":0.08235294,"g":0.9647059,"b":0.43529412},"bg":{"r":0.0,"g":0.0,"b":0.0},"render_order":1}]},{"marker":[7],"components":[{"glyph":234,"fg":{"r":0.08235294,"g":0.9647059,"b":0.43529412},"bg":{"r":0.0,"g":0.0,"b":0.0},"render_order":1}]},{"marker":[8],"components":[{"glyph":234,"fg":{"r":0.08235294,"g":0.9647059,"b":0.43529412},"bg":{"r":0.0,"g":0.0,"b":0.0},"render_order":1}]},{"marker":[9],"components":[{"glyph":234,"fg":{"r":0.27450982,"g":0.78431374,"b":0.78431374},"bg":{"r":0.0,"g":0.0,"b":0.0},"render_order":1}]},{"marker":[10],"components":[{"glyph":234,"fg":{"r":0.27450982,"g":0.78431374,"b":0.78431374},"bg":{"r":0.0,"g":0.0,"b":0.0},"render_order":1}]},{"marker":[11],"components":[{"glyph":234,"fg":{"r":0.08235294,"g":0.9647059,"b":0.43529412},"bg":{"r":0.0,"g":0.0,"b":0.0},"render_order":1}]},{"marker":[12],"components":[{"glyph":234,"fg":{"r":0.27450982,"g":0.78431374,"b":0.78431374},"bg":{"r":0.0,"g":0.0,"b":0.0},"render_order":1}]},{"marker":[13],"components":[{"glyph":234,"fg":{"r":0.08235294,"g":0.9647059,"b":0.43529412},"bg":{"r":0.0,"g":0.0,"b":0.0},"render_order":1}]},{"marker":[14],"components":[{"glyph":234,"fg":{"r":0.27450982,"g":0.78431374,"b":0.78431374},"bg":{"r":0.0,"g":0.0,"b":0.0},"render_order":1}]},{"marker":[15],"components":[{"glyph":234,"fg":{"r":0.08235294,"g":0.9647059,"b":0.43529412},"bg":{"r":0.0,"g":0.0,"b":0.0},"render_order":1}]},{"marker":[16],"components":[{"glyph":234,"fg":{"r":0.27450982,"g":0.78431374,"b":0.78431374},"bg":{"r":0.0,"g":0.0,"b":0.0},"render_order":1}]},{"marker":[17],"components":[{"glyph":8,"fg":{"r":0.9411765,"g":0.98039216,"b":0.11764706},"bg":{"r":0.0,"g":0.0,"b":0.0},"render_order":1}]},{"marker":[18],"components":[{"glyph":8,"fg":{"r":0.9411765,"g":0.98039216,"b":0.11764706},"bg":{"r":0.0,"g":0.0,"b":0.0},"render_order":1}]},{"marker":[19],"components":[null]},{"marker":[20],"components":[null]},{"marker":[21],"components":[null]},{"marker":[22],"components":[null]},{"marker":[23],"components":[null]},{"marker":[24],"components":[null]},{"marker":[25],"components":[null]},{"marker":[26],"components":[null]},{"marker":[27],"components":[null]},{"marker":[28],"components":[null]},{"marker":[29],"components":[null]},{"marker":[30],"components":[null]},{"marker":[31],"components":[null]},{"marker":[32],"components":[null]},{"marker":[33],"components":[null]},{"marker":[34],"components":[null]},{"marker":[35],"components":[{"glyph":1,"fg":{"r":1.0,"g":0.43529412,"b":0.0},"bg":{"r":0.0,"g":0.0,"b":0.0},"render_order":1}]},{"marker":[36],"components":[{"glyph":1,"fg":{"r":1.0,"g":0.43529412,"b":0.0},"bg":{"r":0.0,"g":0.0,"b":0.0},"render_order":1}]},{"marker":[37],"components":[{"glyph":1,"fg":{"r":1.0,"g":0.43529412,"b":0.0},"bg":{"r":0.0,"g":0.0,"b":0.0},"render_order":1}]},{"marker":[38],"components":[{"glyph":1,"fg":{"r":1.0,"g":0.43529412,"b":0.0},"bg":{"r":0.0,"g":0.0,"b":0.0},"render_order":1}]},{"marker":[39],"components":[{"glyph":1,"fg":{"r":1.0,"g":0.43529412,"b":0.0},"bg":{"r":0.0,"g":0.0,"b":0.0},"render_order":1}]},{"marker":[40],"components":[{"glyph":1,"fg":{"r":1.0,"g":0.43529412,"b":0.0},"bg":{"r":0.0,"g":0.0,"b":0.0},"render_order":1}]},{"marker":[41],"components":[{"glyph":1,"fg":{"r":1.0,"g":0.43529412,"b":0.0},"bg":{"r":0.0,"g":0.0,"b":0.0},"render_order":1}]},{"marker":[42],"components":[{"glyph":1,"fg":{"r":1.0,"g":0.43529412,"b":0.0},"bg":{"r":0.0,"g":0.0,"b":0.0},"render_order":1}]},{"marker":[43],"components":[{"glyph":1,"fg":{"r":1.0,"g":0.43529412,"b":0.0},"bg":{"r":0.0,"g":0.0,"b":0.0},"render_order":1}]},{"marker":[44],"components":[{"glyph":1,"fg":{"r":1.0,"g":0.43529412,"b":0.0},"bg":{"r":0.0,"g":0.0,"b":0.0},"render_order":1}]},{"marker":[45],"components":[{"glyph":1,"fg":{"r":1.0,"g":0.43529412,"b":0.0},"bg":{"r":0.0,"g":0.0,"b":0.0},"render_order":1}]},{"marker":[46],"components":[{"glyph":1,"fg":{"r":1.0,"g":0.43529412,"b":0.0},"bg":{"r":0.0,"g":0.0,"b":0.0},"render_order":1}]},{"marker":[47],"components":[{"glyph":31,"fg":{"r":0.039215688,"g":0.039215688,"b":0.039215688},"bg":{"r":0.0,"g":0.0,"b":0.0},"render_order":1}]},{"marker":[48],"components":[{"glyph":31,"fg":{"r":0.9019608,"g":0.9019608,"b":0.5176471},"bg":{"r":0.0,"g":0.0,"b":0.0},"render_order":1}]},{"marker":[49],"components":[{"glyph":31,"fg":{"r":0.11764706,"g":0.11764706,"b":0.11764706},"bg":{"r":0.0,"g":0.0,"b":0.0},"render_order":1}]},{"marker":[50],"components":[{"glyph":30,"fg":{"r":0.8980392,"g":0.8980392,"b":0.7882353},"bg":{"r":0.0,"g":0.0,"b":0.0},"render_order":1}]},{"marker":[51],"components":[{"glyph":30,"fg":{"r":0.89411765,"g":0.89411765,"b":0.19215687},"bg":{"r":0.0,"g":0.0,"b":0.0},"render_order":1}]},{"marker":[52],"components":[null]}][{"marker":[0],"components":[{}]},{"marker":[1],"components":[null]},{"marker":[2],"components":[null]},{"marker":[3],"components":[null]},{"marker":[4],"components":[null]},{"marker":[5],"components":[null]},{"marker":[6],"components":[null]},{"marker":[7],"components":[null]},{"marker":[8],"components":[null]},{"marker":[9],"components":[null]},{"marker":[10],"components":[null]},{"marker":[11],"components":[null]},{"marker":[12],"components":[null]},{"marker":[13],"components":[null]},{"marker":[14],"components":[null]},{"marker":[15],"components":[null]},{"marker":[16],"components":[null]},{"marker":[17],"components":[null]},{"marker":[18],"components":[null]},{"marker":[19],"components":[null]},{"marker":[20],"components":[null]},{"marker":[21],"components":[null]},{"marker":[22],"components":[null]},{"marker":[23],"components":[null]},{"marker":[24],"components":[null]},{"marker":[25],"components":[null]},{"marker":[26],"components":[null]},{"marker":[27],"components":[null]},{"marker":[28],"components":[null]},{"marker":[29],"components":[null]},{"marker":[30],"components":[null]},{"marker":[31],"components":[null]},{"marker":[32],"components":[null]},{"marker":[33],"components":[null]},{"marker":[34],"components":[null]},{"marker":[35],"components":[null]},{"marker":[36],"components":[null]},{"marker":[37],"components":[null]},{"marker":[38],"components":[null]},{"marker":[39],"components":[null]},{"marker":[40],"components":[null]},{"marker":[41],"components":[null]},{"marker":[42],"components":[null]},{"marker":[43],"components":[null]},{"marker":[44],"components":[null]},{"marker":[45],"components":[null]},{"marker":[46],"components":[null]},{"marker":[47],"components":[null]},{"marker":[48],"components":[null]},{"marker":[49],"components":[null]},{"marker":[50],"components":[null]},{"marker":[51],"components":[null]},{"marker":[52],"components":[null]}][{"marker":[0],"components":[{"name":"O"}]},{"marker":[1],"components":[{"name":"Guney Kapisi"}]},{"marker":[2],"components":[{"name":"Ev Kapisi"}]},{"marker":[3],"components":[{"name":"M2152 Kapisi"}]},{"marker":[4],"components":[{"name":"Guney Kapisi"}]},{"marker":[5],"components":[{"name":"Kuzey Kapisi"}]},{"marker":[6],"components":[{"name":"Guney Kapisi"}]},{"marker":[7],"components":[{"name":"Kutuphane Kapisi"}]},{"marker":[8],"components":[{"name":"Kuzey Kapisi"}]},{"marker":[9],"components":[{"name":"Gizli Kapi"}]},{"marker":[10],"components":[{"name":"Bati Cikisi"}]},{"marker":[11],"components":[{"name":"Meydan Kapisi"}]},{"marker":[12],"components":[{"name":"Kuzey Cikisi"}]},{"marker":[13],"components":[{"name":"Meydan Kapisi"}]},{"marker":[14],"components":[{"name":"Dogu Cikisi"}]},{"marker":[15],"components":[{"name":"Meydan Kapisi"}]},{"marker":[16],"components":[{"name":"Zaman Kapisi"}]},{"marker":[17],"components":[{"name":"Taylan Hoca'nin Kitabi"}]},{"marker":[18],"components":[{"name":"Taylan Hoca'nin Kitabi"}]},{"marker":[19],"components":[{"name":"Gizli Gecit Anahtari"}]},{"marker":[20],"components":[{"name":"Bati Anahtari"}]},{"marker":[21],"components":[{"name":"Siir Parcasi"}]},{"marker":[22],"components":[{"name":"Kitap Kapagi"}]},{"marker":[23],"components":[{"name":"Yapistirici"}]},{"marker":[24],"components":[{"name":"Siir Kitabi"}]},{"marker":[25],"components":[{"name":"Kuzey Anahtari"}]},{"marker":[26],"components":[{"name":"Camii Minare Maketi"}]},{"marker":[27],"components":[{"name":"Camii Gövde Maketi"}]},{"marker":[28],"components":[{"name":"Camii Maketi"}]},{"marker":[29],"components":[{"name":"Dogu Anahtari"}]},{"marker":[30],"components":[{"name":"Nota Kagidi"}]},{"marker":[31],"components":[{"name":"Tuval"}]},{"marker":[32],"components":[{"name":"Kil"}]},{"marker":[33],"components":[{"name":"Garip Bir Kolaj"}]},{"marker":[34],"components":[{"name":"Zaman Kapisi Anahtari"}]},{"marker":[35],"components":[{"name":"Taylan Hoca"}]},{"marker":[36],"components":[{"name":"Gizemli Karakter"}]},{"marker":[37],"components":[{"name":"Osman Bey"}]},{"marker":[38],"components":[{"name":"Zeliha Hanim"}]},{"marker":[39],"components":[{"name":"Zeyneb Hanim"}]},{"marker":[40],"components":[{"name":"Ali Bey"}]},{"marker":[41],"components":[{"name":"Emine Hanim"}]},{"marker":[42],"components":[{"name":"Ahmet Bey"}]},{"marker":[43],"components":[{"name":"Nefise Hanim"}]},{"marker":[44],"components":[{"name":"Almila Hanim"}]},{"marker":[45],"components":[{"name":"Aysila"}]},{"marker":[46],"components":[{"name":"Efe"}]},{"marker":[47],"components":[{"name":"Karbeyaz"}]},{"marker":[48],"components":[{"name":"Naci"}]},{"marker":[49],"components":[{"name":"Pasa"}]},{"marker":[50],"components":[{"name":"Adolf"}]},{"marker":[51],"components":[{"name":"Deli"}]},{"marker":[52],"components":[null]}][{"marker":[0],"components":[null]},{"marker":[1],"components":[null]},{"marker":[2],"components":[null]},{"marker":[3],"components":[null]},{"marker":[4],"components":[null]},{"marker":[5],"components":[null]},{"marker":[6],"components":[null]},{"marker":[7],"components":[null]},{"marker":[8],"components":[null]},{"marker":[9],"components":[null]},{"marker":[10],"components":[null]},{"marker":[11],"components":[null]},{"marker":[12],"components":[null]},{"marker":[13],"components":[null]},{"marker":[14],"components":[null]},{"marker":[15],"components":[null]},{"marker":[16],"components":[null]},{"marker":[17],"components":[{"name":"Book"}]},{"marker":[18],"components":[{"name":"Book"}]},{"marker":[19],"components":[{"name":"SecretGateKey"}]},{"marker":[20],"components":[{"name":"OttomanKey1"}]},{"marker":[21],"components":[{"name":"OttomanRewardPoem"}]},{"marker":[22],"components":[{"name":"OttomanRewardBookCover"}]},{"marker":[23],"components":[{"name":"OttomanRewardGlue"}]},{"marker":[24],"components":[{"name":"OttomanCombinedRewardPoemBook"}]},{"marker":[25],"components":[{"name":"OttomanKey2"}]},{"marker":[26],"components":[{"name":"OttomanRewardMosquePart1"}]},{"marker":[27],"components":[{"name":"OttomanRewardMosquePart2"}]},{"marker":[28],"components":[{"name":"OttomanCombinedRewardMosqueModel"}]},{"marker":[29],"components":[{"name":"OttomanKey3"}]},{"marker":[30],"components":[{"name":"OttomanRewardNotePaper"}]},{"marker":[31],"components":[{"name":"OttomanRewardCanvas"}]},{"marker":[32],"components":[{"name":"OttomanRewardClay"}]},{"marker":[33],"components":[{"name":"OttomanCombinedRewardWeirdCollage"}]},{"marker":[34],"components":[{"name":"OttomanKeyMain"}]},{"marker":[35],"components":[null]},{"marker":[36],"components":[null]},{"marker":[37],"components":[null]},{"marker":[38],"components":[null]},{"marker":[39],"components":[null]},{"marker":[40],"components":[null]},{"marker":[41],"components":[null]},{"marker":[42],"components":[null]},{"marker":[43],"components":[null]},{"marker":[44],"components":[null]},{"marker":[45],"components":[null]},{"marker":[46],"components":[null]},{"marker":[47],"components":[null]},{"marker":[48],"components":[null]},{"marker":[49],"components":[null]},{"marker":[50],"components":[null]},{"marker":[51],"components":[null]},{"marker":[52],"components":[null]}][{"marker":[0],"components":[null]},{"marker":[1],"components":[null]},{"marker":[2],"components":[null]},{"marker":[3],"components":[null]},{"marker":[4],"components":[null]},{"marker":[5],"components":[null]},{"marker":[6],"components":[null]},{"marker":[7],"components":[null]},{"marker":[8],"components":[null]},{"marker":[9],"components":[null]},{"marker":[10],"components":[null]},{"marker":[11],"components":[null]},{"marker":[12],"components":[null]},{"marker":[13],"components":[null]},{"marker":[14],"components":[null]},{"marker":[15],"components":[null]},{"marker":[16],"components":[null]},{"marker":[17],"components":[null]},{"marker":[18],"components":[null]},{"marker":[19],"components":[null]},{"marker":[20],"components":[null]},{"marker":[21],"components":[null]},{"marker":[22],"components":[null]},{"marker":[23],"components":[null]},{"marker":[24],"components":[null]},{"marker":[25],"components":[null]},{"marker":[26],"components":[null]},{"marker":[27],"components":[null]},{"marker":[28],"components":[null]},{"marker":[29],"components":[null]},{"marker":[30],"components":[null]},{"marker":[31],"components":[null]},{"marker":[32],"components":[null]},{"marker":[33],"components":[null]},{"marker":[34],"components":[null]},{"marker":[35],"components":[null]},{"marker":[36],"components":[null]},{"marker":[37],"components":[null]},{"marker":[38],"components":[null]},{"marker":[39],"components":[null]},{"marker":[40],"components":[null]},{"marker":[41],"components":[null]},{"marker":[42],"components":[null]},{"marker":[43],"components":[null]},{"marker":[44],"components":[null]},{"marker":[45],"components":[null]},{"marker":[46],"components":[null]},{"marker":[47],"components":[null]},{"marker":[48],"components":[null]},{"marker":[49],"components":[null]},{"marker":[50],"components":[null]},{"marker":[51],"components":[null]},{"marker":[52],"components":[null]}][{"marker":[0],"components":[null]},{"marker":[1],"components":[null]},{"marker":[2],"components":[null]},{"marker":[3],"components":[null]},{"marker":[4],"components":[null]},{"marker":[5],"components":[null]},{"marker":[6],"components":[null]},{"marker":[7],"components":[null]},{"marker":[8],"components":[null]},{"marker":[9],"components":[null]},{"marker":[10],"components":[null]},{"marker":[11],"components":[null]},{"marker":[12],"components":[null]},{"marker":[13],"components":[null]},{"marker":[14],"components":[null]},{"marker":[15],"components":[null]},{"marker":[16],"components":[null]},{"marker":[17],"components":[null]},{"marker":[18],"components":[null]},{"marker":[19],"components":[null]},{"marker":[20],"components":[null]},{"marker":[21],"components":[null]},{"marker":[22],"components":[null]},{"marker":[23],"components":[null]},{"marker":[24],"components":[null]},{"marker":[25],"components":[null]},{"marker":[26],"components":[null]},{"marker":[27],"components":[null]},{"marker":[28],"components":[null]},{"marker":[29],"components":[null]},{"marker":[30],"components":[null]},{"marker":[31],"components":[null]},{"marker":[32],"components":[null]},{"marker":[33],"components":[null]},{"marker":[34],"components":[null]},{"marker":[35],"components":[null]},{"marker":[36],"components":[null]},{"marker":[37],"components":[null]},{"marker":[38],"components":[null]},{"marker":[39],"components":[null]},{"marker":[40],"components":[null]},{"marker":[41],"components":[null]},{"marker":[42],"components":[null]},{"marker":[43],"components":[null]},{"marker":[44],"components":[null]},{"marker":[45],"components":[null]},{"marker":[46],"components":[null]},{"marker":[47],"components":[null]},{"marker":[48],"components":[null]},{"marker":[49],"components":[null]},{"marker":[50],"components":[null]},{"marker":[51],"components":[null]},{"marker":[52],"components":[null]}][{"marker":[0],"components":[null]},{"marker":[1],"components":[null]},{"marker":[2],"components":[null]},{"marker":[3],"components":[null]},{"marker":[4],"components":[null]},{"marker":[5],"components":[null]},{"marker":[6],"components":[null]},{"marker":[7],"components":[null]},{"marker":[8],"components":[null]},{"marker":[9],"components":[{"key":"SecretGateKey"}]},{"marker":[10],"components":[{"key":"OttomanKey1"}]},{"marker":[11],"components":[null]},{"marker":[12],"components":[{"key":"OttomanKey2"}]},{"marker":[13],"components":[null]},{"marker":[14],"components":[{"key":"OttomanKey3"}]},{"marker":[15],"components":[null]},{"marker":[16],"components":[{"key":"OttomanKeyMain"}]},{"marker":[17],"components":[null]},{"marker":[18],"components":[null]},{"marker":[19],"components":[null]},{"marker":[20],"components":[null]},{"marker":[21],"components":[null]},{"marker":[22],"components":[null]},{"marker":[23],"components":[null]},{"marker":[24],"components":[null]},{"marker":[25],"components":[null]},{"marker":[26],"components":[null]},{"marker":[27],"components":[null]},{"marker":[28],"components":[null]},{"marker":[29],"components":[null]},{"marker":[30],"components":[null]},{"marker":[31],"components":[null]},{"marker":[32],"components":[null]},{"marker":[33],"components":[null]},{"marker":[34],"components":[null]},{"marker":[35],"components":[null]},{"marker":[36],"components":[null]},{"marker":[37],"components":[null]},{"marker":[38],"components":[null]},{"marker":[39],"components":[null]},{"marker":[40],"components":[null]},{"marker":[41],"components":[null]},{"marker":[42],"components":[null]},{"marker":[43],"components":[null]},{"marker":[44],"components":[null]},{"marker":[45],"components":[null]},{"marker":[46],"components":[null]},{"marker":[47],"components":[null]},{"marker":[48],"components":[null]},{"marker":[49],"components":[null]},{"marker":[50],"components":[null]},{"marker":[51],"components":[null]},{"marker":[52],"components":[null]}][{"marker":[0],"components":[null]},{"marker":[1],"components":[null]},{"marker":[2],"components":[null]},{"marker":[3],"components":[null]},{"marker":[4],"components":[null]},{"marker":[5],"components":[null]},{"marker":[6],"components":[null]},{"marker":[7],"components":[null]},{"marker":[8],"components":[null]},{"marker":[9],"components":[null]},{"marker":[10],"components":[null]},{"marker":[11],"components":[null]},{"marker":[12],"components":[null]},{"marker":[13],"components":[null]},{"marker":[14],"components":[null]},{"marker":[15],"components":[null]},{"marker":[16],"components":[null]},{"marker":[17],"components":[null]},{"marker":[18],"components":[null]},{"marker":[19],"components":[null]},{"marker":[20],"components":[null]},{"marker":[21],"components":[null]},{"marker":[22],"components":[null]},{"marker":[23],"components":[null]},{"marker":[24],"components":[null]},{"marker":[25],"components":[null]},{"marker":[26],"components":[null]},{"marker":[27],"components":[null]},{"marker":[28],"components":[null]},{"marker":[29],"components":[null]},{"marker":[30],"components":[null]},{"marker":[31],"components":[null]},{"marker":[32],"components":[null]},{"marker":[33],"components":[null]},{"marker":[34],"components":[null]},{"marker":[35],"components":[null]},{"marker":[36],"components":[null]},{"marker":[37],"components":[null]},{"marker":[38],"components":[null]},{"marker":[39],"components":[null]},{"marker":[40],"components":[null]},{"marker":[41],"components":[null]},{"marker":[42],"components":[null]},{"marker":[43],"components":[null]},{"marker":[44],"components":[null]},{"marker":[45],"components":[null]},{"marker":[46],"components":[null]},{"marker":[47],"components":[null]},{"marker":[48],"components":[null]},{"marker":[49],"components":[null]},{"marker":[50],"components":[null]},{"marker":[51],"components":[null]},{"marker":[52],"components":[null]}][{"marker":[0],"components":[null]},{"marker":[1],"components":[null]},{"marker":[2],"components":[null]},{"marker":[3],"components":[null]},{"marker":[4],"components":[null]},{"marker":[5],"components":[null]},{"marker":[6],"components":[null]},{"marker":[7],"components":[null]},{"marker":[8],"components":[null]},{"marker":[9],"components":[null]},{"marker":[10],"components":[null]},{"marker":[11],"components":[null]},{"marker":[12],"components":[null]},{"marker":[13],"components":[null]},{"marker":[14],"components":[null]},{"marker":[15],"components":[null]},{"marker":[16],"components":[null]},{"marker":[17],"components":[null]},{"marker":[18],"components":[null]},{"marker":[19],"components":[null]},{"marker":[20],"components":[null]},{"marker":[21],"components":[null]},{"marker":[22],"components":[null]},{"marker":[23],"components":[null]},{"marker":[24],"components":[null]},{"marker":[25],"components":[null]},{"marker":[26],"components":[null]},{"marker":[27],"components":[null]},{"marker":[28],"components":[null]},{"marker":[29],"components":[null]},{"marker":[30],"components":[null]},{"marker":[31],"components":[null]},{"marker":[32],"components":[null]},{"marker":[33],"components":[null]},{"marker":[34],"components":[null]},{"marker":[35],"components":[{"items":["Book","Book"]}]},{"marker":[36],"components":[{"items":["OttomanCombinedRewardPoemBook","OttomanCombinedRewardMosqueModel","OttomanCombinedRewardWeirdCollage"]}]},{"marker":[37],"components":[{"items":[]}]},{"marker":[38],"components":[{"items":[]}]},{"marker":[39],"components":[{"items":[]}]},{"marker":[40],"components":[{"items":[]}]},{"marker":[41],"components":[{"items":[]}]},{"marker":[42],"components":[{"items":[]}]},{"marker":[43],"components":[{"items":[]}]},{"marker":[44],"components":[{"items":[]}]},{"marker":[45],"components":[{"items":[]}]},{"marker":[46],"components":[{"items":[]}]},{"marker":[47],"components":[{"items":[]}]},{"marker":[48],"components":[{"items":[]}]},{"marker":[49],"components":[{"items":[]}]},{"marker":[50],"components":[{"items":[]}]},{"marker":[51],"components":[{"items":[]}]},{"marker":[52],"components":[null]}][{"marker":[0],"components":[null]},{"marker":[1],"components":[null]},{"marker":[2],"components":[null]},{"marker":[3],"components":[null]},{"marker":[4],"components":[null]},{"marker":[5],"components":[null]},{"marker":[6],"components":[null]},{"marker":[7],"components":[null]},{"marker":[8],"components":[null]},{"marker":[9],"components":[null]},{"marker":[10],"components":[null]},{"marker":[11],"components":[null]},{"marker":[12],"components":[null]},{"marker":[13],"components":[null]},{"marker":[14],"components":[null]},{"marker":[15],"components":[null]},{"marker":[16],"components":[null]},{"marker":[17],"components":[null]},{"marker":[18],"components":[null]},{"marker":[19],"components":[null]},{"marker":[20],"components":[null]},{"marker":[21],"components":[null]},{"marker":[22],"components":[null]},{"marker":[23],"components":[null]},{"marker":[24],"components":[null]},{"marker":[25],"components":[null]},{"marker":[26],"components":[null]},{"marker":[27],"components":[null]},{"marker":[28],"components":[null]},{"marker":[29],"components":[null]},{"marker":[30],"components":[null]},{"marker":[31],"components":[null]},{"marker":[32],"components":[null]},{"marker":[33],"components":[null]},{"marker":[34],"components":[null]},{"marker":[35],"components":[{"items":["SecretGateKey"]}]},{"marker":[36],"components":[{"items":["OttomanKey1","OttomanKey2","OttomanKey3","OttomanKeyMain"]}]},{"marker":[37],"components":[{"items":["OttomanRewardPoem"]}]},{"marker":[38],"components":[{"items":["OttomanRewardBookCover"]}]},{"marker":[39],"components":[{"items":["OttomanRewardGlue"]}]},{"marker":[40],"components":[{"items":["OttomanRewardMosquePart1"]}]},{"marker":[41],"components":[{"items":["OttomanRewardMosquePart2"]}]},{"marker":[42],"components":[{"items":["OttomanRewardNotePaper"]}]},{"marker":[43],"components":[{"items":["OttomanRewardCanvas"]}]},{"marker":[44],"components":[{"items":["OttomanRewardClay"]}]},{"marker":[45],"components":[{"items":[]}]},{"marker":[46],"components":[{"items":[]}]},{"marker":[47],"components":[{"items":[]}]},{"marker":[48],"components":[{"items":[]}]},{"marker":[49],"components":[{"items":[]}]},{"marker":[50],"components":[{"items":[]}]},{"marker":[51],"components":[{"items":[]}]},{"marker":[52],"components":[null]}][{"marker":[0],"components":[null]},{"marker":[1],"components":[null]},{"marker":[2],"components":[null]},{"marker":[3],"components":[null]},{"marker":[4],"components":[null]},{"marker":[5],"components":[null]},{"marker":[6],"components":[null]},{"marker":[7],"components":[null]},{"marker":[8],"components":[null]},{"marker":[9],"components":[null]},{"marker":[10],"components":[null]},{"marker":[11],"components":[null]},{"marker":[12],"components":[null]},{"marker":[13],"components":[null]},{"marker":[14],"components":[null]},{"marker":[15],"components":[null]},{"marker":[16],"components":[null]},{"marker":[17],"components":[{}]},{"marker":[18],"components":[{}]},{"marker":[19],"components":[null]},{"marker":[20],"components":[null]},{"marker":[21],"components":[null]},{"marker":[22],"components":[null]},{"marker":[23],"components":[null]},{"marker":[24],"components":[null]},{"marker":[25],"components":[null]},{"marker":[26],"components":[null]},{"marker":[27],"components":[null]},{"marker":[28],"components":[null]},{"marker":[29],"components":[null]},{"marker":[30],"components":[null]},{"marker":[31],"components":[null]},{"marker":[32],"components":[null]},{"marker":[33],"components":[null]},{"marker":[34],"components":[null]},{"marker":[35],"components":[null]},{"marker":[36],"components":[null]},{"marker":[37],"components":[null]},{"marker":[38],"components":[null]},{"marker":[39],"components":[null]},{"marker":[40],"components":[null]},{"marker":[41],"components":[null]},{"marker":[42],"components":[null]},{"marker":[43],"components":[null]},{"marker":[44],"components":[null]},{"marker":[45],"components":[null]},{"marker":[46],"components":[null]},{"marker":[47],"components":[null]},{"marker":[48],"components":[null]},{"marker":[49],"components":[null]},{"marker":[50],"components":[null]},{"marker":[51],"components":[null]},{"marker":[52],"components":[null]}][{"marker":[0],"components":[null]},{"marker":[1],"components":[null]},{"marker":[2],"components":[null]},{"marker":[3],"components":[null]},{"marker":[4],"components":[null]},{"marker":[5],"components":[null]},{"marker":[6],"components":[null]},{"marker":[7],"components":[null]},{"marker":[8],"components":[null]},{"marker":[9],"components":[null]},{"marker":[10],"components":[null]},{"marker":[11],"components":[null]},{"marker":[12],"components":[null]},{"marker":[13],"components":[null]},{"marker":[14],"components":[null]},{"marker":[15],"components":[null]},{"marker":[16],"components":[null]},{"marker":[17],"components":[null]},{"marker":[18],"components":[null]},{"marker":[19],"components":[null]},{"marker":[20],"components":[null]},{"marker":[21],"components":[null]},{"marker":[22],"components":[null]},{"marker":[23],"components":[null]},{"marker":[24],"components":[null]},{"marker":[25],"components":[null]},{"marker":[26],"components":[null]},{"marker":[27],"components":[null]},{"marker":[28],"components":[null]},{"marker":[29],"components":[null]},{"marker":[30],"components":[null]},{"marker":[31],"components":[null]},{"marker":[32],"components":[null]},{"marker":[33],"components":[null]},{"marker":[34],"components":[null]},{"marker":[35],"components":[null]},{"marker":[36],"components":[null]},{"marker":[37],"components":[null]},{"marker":[38],"components":[null]},{"marker":[39],"components":[null]},{"marker":[40],"components":[null]},{"marker":[41],"components":[null]},{"marker":[42],"components":[null]},{"marker":[43],"components":[null]},{"marker":[44],"components":[null]},{"marker":[45],"components":[null]},{"marker":[46],"components":[null]},{"marker":[47],"components":[null]},{"marker":[48],"components":[null]},{"marker":[49],"components":[null]},{"marker":[50],"components":[null]},{"marker":[51],"components":[null]},{"marker":[52],"components":[{"map":{"tiles":["Space","Space","Space","Space","Space","Space","Space","Space","Space","Space","Space","Space","Space","Space","Space","Space","Space","Space","Space","Space","Space","Space","Space","Space","Space","Space","Space","Space","Space","Space","Space","Space","Space","Space","Space","Space","Space","Space","Space","Space","Space","Space","Space","Space","Space","Space","Space","Space","Space","Space","Space","Space","Space","Space","Space","Space","Space","Space","Space","Space","Space","Space","Space","Space","Space","Space","Space","Space","Space","Space","Space","Space","Space","Space","Space","Space","Space","Space","Space","Space","Space","Space","Space","Space","Space","Space","Space","Space","Space","Space","Space","Space","Space","Space","Space","Space","Space","Space","Space","Space","Space","Space","Space","Space","Space","Space","Space","Space","Space","Space","Space","Space","Space","Space","Space","Space","Space","Space","Space","Space","Space","Space","Space","Space","Space","Space","Space","Space","Space","Space","Space","Space","Space","Space","Space","Space","Space","Space","Space","Space","Space","Space","Space","Space","Space","Space","Space","Space","Space","Space","Space","Space","Space","Space","Space","Space","Space","Space","Space","Space","Space","Space","Space","Space","Space","Space","Space","Space","Space","Space","Space","Space","Space","Space","Space","Space","Space","Space","Space","Space","Space","Space","Space","Space","Space","Space","Space","Space","Space","Space","Space","Space","Space","Space","Space","Space","Space","Space","Space","Space","Space","Space","Space","Space","Space","Space","Space","Space","Space","Space","Space","Space","Space","Space","Space","Space","Space","Space","Space","Space","Space","Space","Space","Space","Space","Space","Space","Space","Space","Space","Space","Space","Space","Space","Space","Space","Space","Space","Space","Space","Space","Space","Space","Space","Space","Space","Space","Space","Space","Space","Space","Space","Space","Space","Space","Space","Space","Space","Space","Space","Space","Space","Space","Space","Space","Space","Space","Space","Space","Space","Space","Space","Space","Space","Space","Space","Space","Space","Space","Space","Space","Space","Space","Space","Space","Space","Space","Space","Space","Space","Space","Space","Space","Space","Space","Space","Space","Space","Space","Space","Space","Space","Space","Space","Space","Space","Space","Space","Space","Space","Space","Space","Space","Space","Space","Space","Space","Space","Space","Space","Space","Space","Space","Space","Space","Space","Space","Space","Space","Space","Space","Space","Space","Space","Space","Space","Space","Space","Space","Space","Space","Space","Space","Space","Space","Space","Space","Space","Space","Space","Space","Space","Space","Space","Space","Space","Space","Space","Space","Space","Space","Space","Space","Space","Space","Space","Space","Space","Space","Space","Space","Space","Space","Space","Space","Space","Space","Space","Space","Space","Space","Space","Space","Space","Space","Space","Space","Space","Space","Space","Space","Space","Space","Space","Space","Space","Space","Space","Space","Space","Space","Space","Space","Space","Space","Space","Space","Space","Space","Space","Space","Space","Space","Space","Space","Space","Space","Space","Space","Space","Space","Space","Space","Space","Space","Space","Space","Space","Space","Space","Space","Space","Space","Space","Space","Space","Space","Space","Space","Space","Space","Space","Space","Space","Space","Space","Space","Space","Space","Space","Space","Space","Space","Space","Space","Space","Space","Space","Space","Space","Space","Space","Space","Space","Space","Space","Space","Space","Space","Space","Space","Space","Space","Space","Space","Space","Space","Space","Space","Space","Space","Space","Space","Space","Space","Space","Space","Space","Space","Space","Space","Space","Space","Space","Space","Space","Space","Space","Space","Space","Space","Space","Space","Space","Space","Space","Space","Space","Space","Space","Space","Space","Space","Space","Space","Space","Space","Space","Space","Space","Space","Space","Space","Space","Space","Space","Space","Space","Space","Space","Space","Space","Space","Space","Space","Space","Space","Space","Space","Space","Space","Space","Space","Space","Space","Space","Space","Space","Space","Space","Space","Space","Space","Space","Space","Space","Space","Space","Space","Space","Space","Space","Space","Space","Space","Space","Space","Space","Space","Space","Space","Space","Space","Space","Space","Space","Space","Space","Space","Space","Space","Space","Space","Space","Space","Space","Space","Space","Space","Space","Space","Space","Space","Space","Space","Space","Space","Space","Space","Space","Space","Space","Space","Space","Space","Space","Space","Space","Space","Space","Space","Space","Space","Space","Space","Space","Space","Space","Space","Space","Space","Space","Space","Space","Space","Space","Space","Space","Space","Space","Space","Space","Space","Space","Space","Space","Space","Space","Space","Space","Space","Space","Space","Space","Space","Space","Space","Space","Space","Space","Space","Space","Space","Space","Space","Space","Space","Space","Space","Space","Space","Space","Space","Space","Space","Space","Space","Space","Space","Space","Space","Space","Space","Space","Space","Space","Space","Space","Space","Space","Space","Space","Space","Space","Space","Space","Space","Space","Space","Space","Space","Space","Space","Space","Space","Space","Space","Space","Space","Space","Space","Space","Space","Space","Space","Space","Space","Space","Space","Space","Space","Space","Space","Space","Space","Space","Space","Space","Space","Wall","Wall","Wall","Wall","Wall","Wall","Portal","Wall","Wall","Wall","Wall","Wall","Space","Space","Space","Space","Space","Space","Space","Space","Space","Space","Space","Space","Space","Space","Space","Space","Space","Space","Space","Space","Space","Space","Space","Space","Space","Space","Space","Space","Space","Space","Space","Space","Space","Space","Space","Space","Space","Space","Wall","Floor","Floor","Floor","Floor","Floor","Floor","Floor","Floor","Floor","Floor","Wall","Space","Space","Space","Space","Space","Space","Space","Space","Space","Space","Space","Space","Space","Space","Space","Space","Space","Space","Space","Space","Space","Space","Space","Space","Space","Space","Space","Space","Space","Space","Space","Space","Space","Space","Space","Space","Space","Space","Wall","Floor","Floor","Floor","Floor","Floor","Floor","Floor","Floor","Floor","Floor","Wall","Space","Space","Space","Space","Space","Space","Space","Space","Space","Space","Space","Space","Space","Space","Space","Space","Space","Space","Space","Space","Space","Space","Space","Space","Space","Space","Space","Space","Space","Space","Space","Space","Space","Space","Space","Space","Space","Space","Wall","Floor","Floor","Floor","Floor","Floor","Floor","Floor","Floor","Floor","Floor","Wall","Space","Space","Space","Space","Space","Space","Space","Space","Space","Space","Space","Space","Space","Space","Space","Space","Space","Space","Space","Space","Space","Space","Space","Space","Space","Space","Space","Space","Space","Space","Space","Space","Space","Space","Space","Space","Space","Space","Wall","Floor","Floor","Floor","Floor","Floor","Floor","Floor","Floor","Floor","Floor","Wall","Space","Space","Space","Space","Space","Space","Space","Space","Space","Space","Space","Space","Space","Space","Space","Space","Space","Space","Space","Space","Space","Space","Space","Space","Space","Space","Space","Space","Space","Space","Space","Space","Space","Space","Space","Space","Space","Space","Wall","Floor","Floor","Floor","Floor","Floor","Floor","Floor","Floor","Floor","Floor","Wall","Space","Space","Space","Space","Space","Space","Space","Space","Space","Space","Space","Space","Space","Space","Space","Space","Space","Space","Space","Space","Space","Space","Space","Space","Space","Space","Space","Space","Space","Space","Space","Space","Space","Space","Space","Space","Space","Space","Wall","Floor","Floor","Floor","Floor","Floor","Floor","Floor","Floor","Floor","Floor","Wall","Space","Space","Space","Space","Space","Space","Space","Space","Space","Space","Space","Space","Space","Space","Space","Space","Space","Space","Space","Space","Space","Space","Space","Space","Space","Space","Space","Space","Space","Space","Space","Space","Space","Space","Space","Space","Space","Space","Wall","Floor","Floor","Floor","Floor","Floor","Floor","Floor","Floor","Floor","Floor","Wall","Space","Space","Space","Space","Space","Space","Space","Space","Space","Space","Space","Space","Space","Space","Space","Space","Space","Space","Space","Space","Space","Space","Space","Space","Space","Space","Space","Space","Space","Space","Space","Space","Space","Space","Space","Space","Space","Space","Wall","Floor","Floor","Floor","Floor","Floor","Floor","Floor","Floor","Floor","Floor","Wall","Space","Space","Space","Space","Space","Space","Space","Space","Space","Space","Space","Space","Space","Space","Space","Space","Space","Space","Space","Space","Space","Space","Space","Space","Space","Space","Space","Space","Space","Space","Space","Space","Space","Space","Space","Space","Space","Space","Wall","Floor","Floor","Floor","Floor","Floor","Floor","Floor","Floor","Floor","Floor","Wall","Space","Space","Space","Space","Space","Space","Space","Space","Space","Space","Space","Space","Space","Space","Space","Space","Space","Space","Space","Space","Space","Space","Space","Space","Space","Space","Space","Space","Space","Space","Space","Space","Space","Space","Space","Space","Space","Space","Wall","Floor","Floor","Floor","Floor","Floor","Floor","Floor","Floor","Floor","Floor","Wall","Space","Space","Space","Space","Space","Space","Space","Space","Space","Space","Space","Space","Space","Space","Space","Space","Space","Space","Space","Space","Space","Space","Space","Space","Space","Space","Space","Space","Space","Space","Space","Space","Space","Space","Space","Space","Space","Space","Wall","Wall","Wall","Wall","Wall","Wall","Wall","Wall","Wall","Wall","Wall","Wall","Space","Space","Space","Space","Space","Space","Space","Space","Space","Space","Space","Space","Space","Space","Space","Space","Space","Space","Space","Space","Space","Space","Space","Space","Space","Space","Space","Space","Space","Space","Space","Space","Space","Space","Space","Space","Space","Space","Space","Space","Space","Space","Space","Space","Space","Space","Space","Space","Space","Space","Space","Space","Space","Space","Space","Space","Space","Space","Space","Space","Space","Space","Space","Space","Space","Space","Space","Space","Space","Space","Space","Space","Space","Space","Space","Space","Space","Space","Space","Space","Space","Space","Space","Space","Space","Space","Space","Space","Space","Space","Space","Space","Space","Space","Space","Space","Space","Space","Space","Space","Space","Space","Space","Space","Space","Space","Space","Space","Space","Space","Space","Space","Space","Space","Space","Space","Space","Space","Space","Space","Space","Space","Space","Space","Space","Space","Space","Space","Space","Space","Space","Space","Space","Space","Space","Space","Space","Space","Space","Space","Space","Space","Space","Space","Space","Space","Space","Space","Space","Space","Space","Space","Space","Space","Space","Space","Space","Space","Space","Space","Space","Space","Space","Space","Space","Space","Space","Space","Space","Space","Space","Space","Space","Space","Space","Space","Space","Space","Space","Space","Space","Space","Space","Space","Space","Space","Space","Space","Space","Space","Space","Space","Space","Space","Space","Space","Space","Space","Space","Space","Space","Space","Space","Space","Space","Space","Space","Space","Space","Space","Space","Space","Space","Space","Space","Space","Space","Space","Space","Space","Space","Space","Space","Space","Space","Space","Space","Space","Space","Space","Space","Space","Space","Space","Space","Space","Space","Space","Space","Space","Space","Space","Space","Space","Space","Space","Space","Space","Space","Space","Space","Space","Space","Space","Space","Space","Space","Space","Space","Space","Space","Space","Space","Space","Space","Space","Space","Space","Space","Space","Space","Space","Space","Space","Space","Space","Space","Space","Space","Space","Space","Space","Space","Space","Space","Space","Space","Space","Space","Space","Space","Space","Space","Space","Space","Space","Space","Space","Space","Space","Space","Space","Space","Space","Space","Space","Space","Space","Space","Space","Space","Space","Space","Space","Space","Space","Space","Space","Space","Space","Space","Space","Space","Space","Space","Space","Space","Space","Space","Space","Space","Space","Space","Space","Space","Space","Space","Space","Space","Space","Space","Space","Space","Space","Space","Space","Space","Space","Space","Space","Space","Space","Space","Space","Space","Space","Space","Space","Space","Space","Space","Space","Space","Space","Space","Space","Space","Space","Space","Space","Space","Space","Space","Space","Space","Space","Space","Space","Space","Space","Space","Space","Space","Space","Space","Space","Space","Space","Space","Space","Space","Space","Space","Space","Space","Space","Space","Space","Space","Space","Space","Space","Space","Space","Space","Space","Space","Space","Space","Space","Space","Space","Space","Space","Space","Space","Space","Space","Space","Space","Space","Space","Space","Space","Space","Space","Space","Space","Space","Space","Space","Space","Space","Space","Space","Space","Space","Space","Space","Space","Space","Space","Space","Space","Space","Space","Space","Space","Space","Space","Space","Space","Space","Space","Space","Space","Space","Space","Space","Space","Space","Space","Space","Space","Space","Space","Space","Space","Space","Space","Space","Space","Space","Space","Space","Space","Space","Space","Space","Space","Space","Space","Space","Space","Space","Space","Space","Space","Space","Space","Space","Space","Space","Space","Space","Space","Space","Space","Space","Space","Space","Space","Space","Space","Space","Space","Space","Space","Space","Space","Space","Space","Space","Space","Space","Space","Space","Space","Space","Space","Space","Space","Space","Space","Space","Space","Space","Space","Space","Space","Space","Space","Space","Space","Space","Space","Space","Space","Space","Space","Space","Space","Space","Space","Space","Space","Space","Space","Space","Space","Space","Space","Space","Space","Space","Space","Space","Space","Space","Space","Space","Space","Space","Space","Space","Space","Space","Space","Space","Space","Space","Space","Space","Space","Space","Space","Space","Space","Space","Space","Space","Space","Space","Space","Space","Space","Space","Space","Space","Space","Space","Space","Space","Space","Space","Space","Space","Space","Space","Space","Space","Space","Space","Space","Space","Space","Space","Space","Space","Space","Space","Space","Space","Space","Space","Space","Space","Space","Space","Space","Space","Space","Space","Space","Space","Space","Space","Space","Space","Space","Space","Space","Space","Space","Space","Space","Space","Space","Space","Space","Space","Space","Space","Space","Space","Space","Space","Space","Space","Space","Space","Space","Space","Space","Space","Space","Space","Space","Space","Space","Space","Space","Space","Space","Space","Space","Space","Space","Space","Space","Space","Space","Space","Space","Space","Space","Space","Space","Space","Space","Space","Space","Space","Space","Space","Space","Space","Space","Space","Space","Space","Space","Space","Space","Space","Space","Space","Space","Space","Space","Space","Space","Space","Space","Space","Space","Space","Space","Space","Space","Space","Space","Space","Space","Space","Space","Space","Space","Space"],"width":50,"height":40,"place":"Home"}}]}][{"marker":[0],"components":[null]},{"marker":[1],"components":[{"target":"SchoolSouth","warp_place":[24,29]}]},{"marker":[2],"components":[{"target":"Home","warp_place":[25,15]}]},{"marker":[3],"components":[{"target":"Class","warp_place":[19,14]}]},{"marker":[4],"components":[{"target":"SchoolSouth","warp_place":[36,20]}]},{"marker":[5],"components":[{"target":"SchoolNorth","warp_place":[35,19]}]},{"marker":[6],"components":[{"target":"SchoolSouth","warp_place":[12,20]}]},{"marker":[7],"components":[{"target":"Library","warp_place":[31,20]}]},{"marker":[8],"components":[{"target":"SchoolNorth","warp_place":[14,19]}]},{"marker":[9],"components":[{"target":"OttomanMain","warp_place":[24,19]}]},{"marker":[10],"components":[{"target":"OttomanLeft","warp_place":[30,20]}]},{"marker":[11],"components":[{"target":"OttomanMain","warp_place":[16,19]}]},{"marker":[12],"components":[{"target":"OttomanTop","warp_place":[25,25]}]},{"marker":[13],"components":[{"target":"OttomanMain","warp_place":[25,10]}]},{"marker":[14],"components":[{"target":"OttomanRight","warp_place":[19,20]}]},{"marker":[15],"components":[{"target":"OttomanMain","warp_place":[33,19]}]},{"marker":[16],"components":[{"target":"SchoolSouth","warp_place":[24,10]}]},{"marker":[17],"components":[null]},{"marker":[18],"components":[null]},{"marker":[19],"components":[null]},{"marker":[20],"components":[null]},{"marker":[21],"components":[null]},{"marker":[22],"components":[null]},{"marker":[23],"components":[null]},{"marker":[24],"components":[null]},{"marker":[25],"components":[null]},{"marker":[26],"components":[null]},{"marker":[27],"components":[null]},{"marker":[28],"components":[null]},{"marker":[29],"components":[null]},{"marker":[30],"components":[null]},{"marker":[31],"components":[null]},{"marker":[32],"components":[null]},{"marker":[33],"components":[null]},{"marker":[34],"components":[null]},{"marker":[35],"components":[null]},{"marker":[36],"components":[null]},{"marker":[37],"components":[null]},{"marker":[38],"components":[null]},{"marker":[39],"components":[null]},{"marker":[40],"components":[null]},{"marker":[41],"components":[null]},{"marker":[42],"components":[null]},{"marker":[43],"components":[null]},{"marker":[44],"components":[null]},{"marker":[45],"components":[null]},{"marker":[46],"components":[null]},{"marker":[47],"components":[null]},{"marker":[48],"components":[null]},{"marker":[49],"components":[null]},{"marker":[50],"components":[null]},{"marker":[51],"components":[null]},{"marker":[52],"components":[null]}][{"marker":[0],"components":[{"domain":"Home"}]},{"marker":[1],"components":[{"domain":"Home"}]},{"marker":[2],"components":[{"domain":"SchoolSouth"}]},{"marker":[3],"components":[{"domain":"SchoolSouth"}]},{"marker":[4],"components":[{"domain":"Class"}]},{"marker":[5],"components":[{"domain":"SchoolSouth"}]},{"marker":[6],"components":[{"domain":"SchoolNorth"}]},{"marker":[7],"components":[{"domain":"SchoolNorth"}]},{"marker":[8],"components":[{"domain":"Library"}]},{"marker":[9],"components":[{"domain":"SchoolSouth"}]},{"marker":[10],"components":[{"domain":"OttomanMain"}]},{"marker":[11],"components":[{"domain":"OttomanLeft"}]},{"marker":[12],"components":[{"domain":"OttomanMain"}]},{"marker":[13],"components":[{"domain":"OttomanTop"}]},{"marker":[14],"components":[{"domain":"OttomanMain"}]},{"marker":[15],"components":[{"domain":"OttomanRight"}]},{"marker":[16],"components":[{"domain":"OttomanMain"}]},{"marker":[17],"components":[{"domain":"Library"}]},{"marker":[18],"components":[{"domain":"Library"}]},{"marker":[19],"components":[null]},{"marker":[20],"components":[null]},{"marker":[21],"components":[null]},{"marker":[22],"components":[null]},{"marker":[23],"components":[null]},{"marker":[24],"components":[null]},{"marker":[25],"components":[null]},{"marker":[26],"components":[null]},{"marker":[27],"components":[null]},{"marker":[28],"components":[null]},{"marker":[29],"components":[null]},{"marker":[30],"components":[null]},{"marker":[31],"components":[null]},{"marker":[32],"components":[null]},{"marker":[33],"components":[null]},{"marker":[34],"components":[null]},{"marker":[35],"components":[{"domain":"Class"}]},{"marker":[36],"components":[{"domain":"OttomanMain"}]},{"marker":[37],"components":[{"domain":"OttomanLeft"}]},{"marker":[38],"components":[{"domain":"OttomanLeft"}]},{"marker":[39],"components":[{"domain":"OttomanLeft"}]},{"marker":[40],"components":[{"domain":"OttomanTop"}]},{"marker":[41],"components":[{"domain":"OttomanTop"}]},{"marker":[42],"components":[{"domain":"OttomanRight"}]},{"marker":[43],"components":[{"domain":"OttomanRight"}]},{"marker":[44],"components":[{"domain":"OttomanRight"}]},{"marker":[45],"components":[{"domain":"SchoolSouth"}]},{"marker":[46],"components":[{"domain":"SchoolSouth"}]},{"marker":[47],"components":[{"domain":"SchoolNorth"}]},{"marker":[48],"components":[{"domain":"SchoolNorth"}]},{"marker":[49],"components":[{"domain":"SchoolNorth"}]},{"marker":[50],"components":[{"domain":"SchoolNorth"}]},{"marker":[51],"components":[{"domain":"SchoolNorth"}]},{"marker":[52],"components":[null]}][{"marker":[0],"components":[null]},{"marker":[1],"components":[null]},{"marker":[2],"components":[null]},{"marker":[3],"components":[null]},{"marker":[4],"components":[null]},{"marker":[5],"components":[null]},{"marker":[6],"components":[null]},{"marker":[7],"components":[null]},{"marker":[8],"components":[null]},{"marker":[9],"components":[null]},{"marker":[10],"components":[null]},{"marker":[11],"components":[null]},{"marker":[12],"components":[null]},{"marker":[13],"components":[null]},{"marker":[14],"components":[null]},{"marker":[15],"components":[null]},{"marker":[16],"components":[null]},{"marker":[17],"components":[null]},{"marker":[18],"components":[null]},{"marker":[19],"components":[null]},{"marker":[20],"components":[null]},{"marker":[21],"components":[null]},{"marker":[22],"components":[null]},{"marker":[23],"components":[null]},{"marker":[24],"components":[null]},{"marker":[25],"components":[null]},{"marker":[26],"components":[null]},{"marker":[27],"components":[null]},{"marker":[28],"components":[null]},{"marker":[29],"components":[null]},{"marker":[30],"components":[null]},{"marker":[31],"components":[null]},{"marker":[32],"components":[null]},{"marker":[33],"components":[null]},{"marker":[34],"components":[null]},{"marker":[35],"components":[{"state":"HasDialogue"}]},{"marker":[36],"components":[{"state":"HasDialogue"}]},{"marker":[37],"components":[{"state":"HasDialogue"}]},{"marker":[38],"components":[{"state":"HasDialogue"}]},{"marker":[39],"components":[{"state":"HasDialogue"}]},{"marker":[40],"components":[{"state":"HasDialogue"}]},{"marker":[41],"components":[{"state":"HasDialogue"}]},{"marker":[42],"components":[{"state":"HasDialogue"}]},{"marker":[43],"components":[{"state":"HasDialogue"}]},{"marker":[44],"components":[{"state":"HasDialogue"}]},{"marker":[45],"components":[{"state":"HasDialogue"}]},{"marker":[46],"components":[{"state":"HasDialogue"}]},{"marker":[47],"components":[{"state":"HasDialogue"}]},{"marker":[48],"components":[{"state":"HasDialogue"}]},{"marker":[49],"components":[{"state":"HasDialogue"}]},{"marker":[50],"components":[{"state":"HasDialogue"}]},{"marker":[51],"components":[{"state":"HasDialogue"}]},{"marker":[52],"components":[null]}][{"marker":[0],"components":[null]},{"marker":[1],"components":[null]},{"marker":[2],"components":[null]},{"marker":[3],"components":[null]},{"marker":[4],"components":[null]},{"marker":[5],"components":[null]},{"marker":[6],"components":[null]},{"marker":[7],"components":[null]},{"marker":[8],"components":[null]},{"marker":[9],"components":[null]},{"marker":[10],"components":[null]},{"marker":[11],"components":[null]},{"marker":[12],"components":[null]},{"marker":[13],"components":[null]},{"marker":[14],"components":[null]},{"marker":[15],"components":[null]},{"marker":[16],"components":[null]},{"marker":[17],"components":[null]},{"marker":[18],"components":[null]},{"marker":[19],"components":[null]},{"marker":[20],"components":[null]},{"marker":[21],"components":[null]},{"marker":[22],"components":[null]},{"marker":[23],"components":[null]},{"marker":[24],"components":[null]},{"marker":[25],"components":[null]},{"marker":[26],"components":[null]},{"marker":[27],"components":[null]},{"marker":[28],"components":[null]},{"marker":[29],"components":[null]},{"marker":[30],"components":[null]},{"marker":[31],"components":[null]},{"marker":[32],"components":[null]},{"marker":[33],"components":[null]},{"marker":[34],"components":[null]},{"marker":[35],"components":[null]},{"marker":[36],"components":[null]},{"marker":[37],"components":[null]},{"marker":[38],"components":[null]},{"marker":[39],"components":[null]},{"marker":[40],"components":[null]},{"marker":[41],"components":[null]},{"marker":[42],"components":[null]},{"marker":[43],"components":[null]},{"marker":[44],"components":[null]},{"marker":[45],"components":[null]},{"marker":[46],"components":[null]},{"marker":[47],"components":[null]},{"marker":[48],"components":[null]},{"marker":[49],"components":[null]},{"marker":[50],"components":[null]},{"marker":[51],"components":[null]},{"marker":[52],"components":[null]}][{"marker":[0],"components":[null]},{"marker":[1],"components":[null]},{"marker":[2],"components":[null]},{"marker":[3],"components":[null]},{"marker":[4],"components":[null]},{"marker":[5],"components":[null]},{"marker":[6],"components":[null]},{"marker":[7],"components":[null]},{"marker":[8],"components":[null]},{"marker":[9],"components":[null]},{"marker":[10],"components":[null]},{"marker":[11],"components":[null]},{"marker":[12],"components":[null]},{"marker":[13],"components":[null]},{"marker":[14],"components":[null]},{"marker":[15],"components":[null]},{"marker":[16],"components":[null]},{"marker":[17],"components":[null]},{"marker":[18],"components":[null]},{"marker":[19],"components":[null]},{"marker":[20],"components":[null]},{"marker":[21],"components":[null]},{"marker":[22],"components":[null]},{"marker":[23],"components":[null]},{"marker":[24],"components":[null]},{"marker":[25],"components":[null]},{"marker":[26],"components":[null]},{"marker":[27],"components":[null]},{"marker":[28],"components":[null]},{"marker":[29],"components":[null]},{"marker":[30],"components":[null]},{"marker":[31],"components":[null]},{"marker":[32],"components":[null]},{"marker":[33],"components":[null]},{"marker":[34],"components":[null]},{"marker":[35],"components":[{"dialogues":[["Merhabalar","Bugun derste gosterecegim kitaplari kutuphanede unutmusum"],["Rica etsem kitaplari getirebilir misiniz?"],["Super, iki tane daha olmali"],["Cok tesekkurler","Sonuncuyu da alabilir miyim?"],["Demek sizde degil","O zaman size bu anahtari veriyorum","Guney Kampus'te biraz gezerseniz bu anahtarin kullnailacagi bir kapi bulacaksiniz ve kitabim de o kapinin ardinda"],["Iyi gunler","Kitabi bulmayi unutmayin"]],"dialogue_index":0,"get_item_indices":[1,2],"give_item_indices":[4],"change_objective_indices":[1,4],"repeat":false,"print_no_item":true}]},{"marker":[36],"components":[{"dialogues":[["Merhabalar gelecekten gelen","Yuzundeki ifadeden anladigim kadariyla oldukca sasirmis durumdasin ","O yuzden aciklamama izin ver:"],["Taylan Hoca, tarihi ogrenmek icin bir caba icerisinde olmayanlara iyi bir ders vermek icin onlari gecmise yollar","Bu sefer de o sansli kisi sensin belli ki"],["Eger kendi zamanina donmek istiyorsan dersini burada, yasayarak ogrenmek zorundasin","Bu seneki konu Osmanli'da sanat","Gordugun kapilarin arkasinda, konu hakkinda seni ilgilendirecek insanlar bulunuyor","Her birini iyice dinle ve isin bitince bana geri don"],["Hadi bakalim","Ilk ders ile basla"],["Demek ilk dersi dinledin","Afferin"],["Simdi sirada ikinci ders var"],["Dersi dinle ve bana geri don"],["Demek ikinci dersi dinledin","Afferin"],["Simdi ucuncu ders"],["Dersi dinle ve bana geri don"],["Demek ucuncu dersi dinledin","Afferin","Artik kendi zamanina donebilirsin"],["Kendine iyi bak"]],"dialogue_index":0,"get_item_indices":[3,6,9],"give_item_indices":[2,5,8,10],"change_objective_indices":[2,5,8,10],"repeat":false,"print_no_item":true}]},{"marker":[37],"components":[{"dialogues":[["Medeniyetler, birbirinden ayri dusunulemezler. Bu sebepten mutevellit, medeniyetler arasindaki etkilesimin bir sekilde saglanmasi gerekir. Bu etkilesim de tercume sayesinde paylasilir. Tercumeye gerekli degeri ilk verenler Tanzimat dusunurleriydi. Sinasi’nin 1869’da Fransiz siirlerini cevirmesinden sonra 1880’e kadar sadece 25 siir tercume edildi. Neyse ki 1880’den sonra bati ulkelerine ait siirlerin tercume edilip dilimize aktarilmasi bir hayli hiz kazandi."],["1859-1901 yillari arasinda Bati edebiyatindan en az 802 siir dilimize tercume edildi ve bu sayede bizim siirlerimizde de farkli formlar ve konular gorulmeye baslandi. Bu farkli konulardan belki de en onemlisi, tekrardan bireylerin gunluk problemlerinin siirlere aktarilmasiydi. O donemin onemli sair-mutercimlerine Muallim Naci, Ahmed Rasim, Recâizâde Mahmud Ekrem, Şinasi ve Nâbizâde Nâzim gibi isimleri; daha cok mutercimlikleri ile bilinen isimlere Halil Edib, Ahmed Refik ve Ali Riza Seyfi gibi isimleri ornek verebilirim."],["Seninle ilginc bir bilgi paylasmak istiyorum: Su yenililesme karsiti diye anilan Muallim Naci var ya; belirttigim yillar arasinda 62 manzume ile en fazla tercume yapan sairimiz odur.  Yapilan siir cevirilerinin buyuk bir cogunlugu 650 siir ile Fransiz edebiyatina aitti ve devaminda Ingiliz ve Alman edebiyati geliyordu. Yapilan tercumelerin gazetelerde yayinlanmasi ve gunluk hayatin bir parcasi haline gelmesi, Bati siirine olan ilgiyi daha da arttirmistir. Bu ilgiden kaynakli olarak daha once de belirttigim gibi yeni siir formlari ortaya cikmaya basladi."],["Bu durum hem bir zenginlige ve duzensizlige kapi acmis oldu. Neden oldugunu anlayamasam da fabller Bati siir dunyasi icerisinde onemli bir yer kaplamakta idi ve tercumeler sayesinde bizim edebiyatimizda da benimsenmis oldu. Yapilan tercumelerin hangi eserlere ait olduklarina bakarken, mutercimlerin kisisel tercihlerinin de bu secimlerde onemli roller oynadigini unutmamak gerekir. Mesela Recaizade Ekrem daha cok La Fontaine’nin fabblerini tercume etmeyi tercih etmistir. Naci ise tercihini Florian’in eserlerinden yana kullanmistir."],["Umarim anlattiklarim faydali olmustur."]],"dialogue_index":0,"get_item_indices":[],"give_item_indices":[3],"change_objective_indices":[3],"repeat":false,"print_no_item":true}]},{"marker":[38],"components":[{"dialogues":[["Tanzimar sonrasi edebiyatinin demirbaslari sayilabilecek kisilerinden Sinasi, Namik Kemal, Recaizade Mahmut Ekrem gibi isimler duzenli bir egitimden gecmediler. Bunun yerine ozel dersler almislardir. Hepsi Fransiz lisanina hakimdiler. Tanzimat’tan sonra baslayan okullasmanin urunu olan okullarda Arapca ogretilmemekteydi. Arapca ve Farsca eserler yerine bati edebiyati eserleri daha cazip gorulmekte, bu eserler okutulmakta, dolayisiyla edebiyati anlayisi da buna gore sekillenmekteydi."],["Namik Kemal, yayimladigi makalesinde (Lisân-i Osmanînin Edebiyati Hakkinda Bazi Mulâhazâti Şamildir) bati rhe- torique’inin prensiplerinden olan hakikat ve tabiata uygunlugu ozellikle vurgulamistir. Namik Kemal’in Avrupa’ya gitmeden Batili eserlerin etkisinde kaldigi buradan anlasilabilir. Bunun devaminda Suleyman Pasa “Mebani’l Insa” adinda, Ali Cemaleddin “Arûz-t Turkî” adinda, Mihalicli Mustafa Efendi ise “Zubdetu’l-Beyan” adinda eserler yayimlarlar ancak hicbiri yeni edebiyat icin bir oncu gorevi goremez."],["Derken 1879’da Recaizade Mahmut Ekrem “Talim-i Edebiyat”’i tas baski halinde cikarmistir. Eserinde edebiyatin degistiginden, bu yeni edebiyatin aciklanmasi gerektiginden bahsetmektedir ve bu ihtiyaci karsilamaya calismistir. Namik Kemal, yazilanlarin konusma dilinde olmasi gerektigini hem sozlerin hem de hayallerin milli olmasi gerektigini, dolayisiyla edebiyati yaklasmakta oldugu Batili fikirlerden de korumak gerektigini vurgulamistir. Milliyet ve vatan meselelerini on plana cikararak yeni bir anlayis ortaya koymustur."],["Dinledigin icin tesekkur ederim."]],"dialogue_index":0,"get_item_indices":[],"give_item_indices":[2],"change_objective_indices":[2],"repeat":false,"print_no_item":true}]},{"marker":[39],"components":[{"dialogues":[["Devletimizin Bati karsisinda surekli guc kaybettigi donemlerde, aydinlarimiz edebiyati halki yasadigi bunalimdan biraz da olsa kurtarabilmek adina kullanmislardir. Bu sebepten dolayi son donem edebiyatimizda sosyal, siyasal, kulturel problemlere atiflara oldukca rastlanir. Son donem yazarlarimizdan Munif Paşa, Ahmet Mithat Efendi, Sadullah Paşa gibi isimler donemin fikir hareketlerinden etkilenerek bu fikirleri eserlerine yansitmislardir. Batidan bizim topraklarimiza ulasan rasyonalist akim da bu fikir akimlarindan biridir."],["Tercume-i Telemak cevirisi, direkt olarak bati dusuncesine dayanan bir kitaptir mesela.Namik Kemal icin cok degerli olarak gorulmesi ve Sinasi tarafindan ikinci baskisinin cevrilmesi, son donem edebiyatcilarimizin rasyonalizm ve realizmin etkisi altinda kaldigini gosterir. Baska bir ornek ise, Mumif Pasa’nin Mecmua-i Funun’da arka arkaya yayinladigi makaleler icerisinde batiya ait calismalardan faydalanilmasi ve bazi calismalarin dogrudan cevirilmesidir."],["Belirtmek istedigim baska bir durum ise, Fransiz aydinlanmasinda buyuk rol oynayan Montesqieu, Voltaire, Jean Jack Rousseau ve Diderot’un akla dayali ansiklopedik bilgiyi edebiyatlari ile birlestirme endiselerini; 1839-1896 yillari arasinda eser ureten edebiyatcilarimizin cogunda da gorebilmekteyiz."],["İyi gunler dilerim."]],"dialogue_index":0,"get_item_indices":[],"give_item_indices":[2],"change_objective_indices":[2],"repeat":false,"print_no_item":true}]},{"marker":[40],"components":[{"dialogues":[["18. yuzyilin baslarindan itibaren Osmanli’nin Bati’nin gerisinde kalmasi, Bati’ya olan ilgiyi arttirmis ve Bati’yi ornek alma istegini kacinilmaz kilmisti. Istanbul’da bulunan Nuruosmaniye Camisi, Bati etkisinin mimari alanda gorulmeye baslandigi ilk orneklerdendir. Ne gibi bir farki vardi diyecek olursan ; avlusu klasik forma sahip diger camilere nazaran oval bir bicimdeydi. Anadolu camilerine deginecek olursak ise; batidan esinlenilen yuvarlak kemerler bulundurmalari, agirlik kulelerine her zaman olmasa da yeni bicimler verilmesi Bati’dan etkilendigimizin baska bir gostergesidir."],["Camilere yerlestirilen kapilarin uzerlerindeki motifler icin de zaman icinde batili tarzda motifler kullanildigini goruyoruz. Baska bir ornek ise 1895 tarihinde tamamlanan Soke Haci Ziya Bey Camii’sinin cephesi itibariyle adete Avrupai bir kosku andirmasidir. Turbeler acisindan bakacak olursak eger, 18. ve 19. Yuzyillar arasinda Anadolu turbe mimarisi onemini giderek yitirmis, sanat degerini kaybetmis ve cagin modasina uyum saglayamamistir. Medreseler, hanlar ve cesmeler, gerek Bati gerek baska fikir akimlari tarafindan etkilenmeyerek, ozlerinden pek kopmamislardir."],["Saraylar, biraz once bahsetmis oldugumuz yapilara nazaran, kendi kulturumuze ait unsurlari bulundurmanin yaninda, daha fazla Avrupai fikirler ile yapilmis unsurlari bunyesinde bulundurmaktadir. Gunluk hayata uyum saglamayi basaran han, carsi gibi yapilar varliklarini surdurmeye devam etmislerdir. Diger geleneksel yapilar ise toplumdaki ve kulturdeki degisimlere uyum saglayamadiklarindan mutevellit onemlerini yitirerek sayica azalmaya baslamislardir."],["Bunun onemli sebeplerinden biri Bati’ya duyulan ozenti sonucunda bakis acilarinin degismesi ve yeni ihtiyaclarin ortaya cikmasidir. Onemini yitirmeyen en onemli yapilar camiilerdir ancak gorunus acisindan daha once de bahsettigim gibi degisimler gecirmisler, batili bicimde gorunum kazanmislardir. Bu degisimlerin sebebi olan Batili gelisme donemleri ise belirli bir sira ile degil, daha cok karma olarak uygulanmistir. Buna ek olarak, camiilerde batili tarzda motiflere, nakislara ve kabartmalara yer verilmistir ve bu Turk resim sanati da degistiren bir degisim olmustur."],["Yabanci sanatcilar Istanbul’a gelerek eser vermisler, kendi bildiklerini yaymaya calismislardir. Bircoguna gore bu sanat alanindaki batililasma icin oncu niteliginde bir olaydir. Bana soracak olursan eger zaten Turk Sanati o donem Avrupa’dan cok etkilenmis bir noktadaydi, onlar ise oncu degil de degisimi hizlandiran etkenler olmuslardir."],["Haydi selametle."]],"dialogue_index":0,"get_item_indices":[],"give_item_indices":[4],"change_objective_indices":[4],"repeat":false,"print_no_item":true}]},{"marker":[41],"components":[{"dialogues":[["17. yuzyilin sonlarinda Lale Devri adinda bir uslup dogmustur. Kullanilan sade desenler, yerini daha karmasik desenlere birakmistir ve Barok uslubu kullanilmaya baslanmistir. Bunun devaminda Rokoko uslubuna gecilmis, daha hafif desenler kullanilmaya devam edilmistir. Barok ve Rokoko uslubunun devaminda ise Ampir uslubuna gecilmistir. Ampir uslubun en onemli orneklerinden biri ise Nusretiye Camii’dir ve 1826’da yapilmistir. Osmanli’nin son donemlerinde Bati ile, ozellikle de Fransa ile, etkilesimlerin artmasi sanati bircok alanda etkilemistir ve mimari de kuskusuz bu alanlardan biridir."],["18. Yuzyilda baslayan ve 19. Yuzyil boyunca devam eden bu etkilenme donemine “Batililasma Hareketi” denmistir. Yurt disindan gelen yabanci mimarlarin Osmanli’da yapi faaliyetlerinin bir parcasi olmalari, batililasmayi hizlandirmistir. Avrupa’da ulusculuk dusuncesinin onem kazanmasi sonucunda gecmise duyulan hayranlik ve ozlem artmis, sonucunda Neo-Klasik uslup dogmustur. Bu uslup cercevesinde cephe duzenlemelerinde gecmise dayanan teknikler kullanilmistir."],["Biraz once bahsetmis oldugum sebeplerden mutevellit, Osmanli mimarisinde ozellikle cephe yapilarinda da benzer degisimler gorulmustur. Yabanci mimarlar ozellikle anitsal yapilar uzerine calismislardir. 1890 yilinda tamamlanan Istanbul Sirkeci Gari, Osmanli ve Alman Mimari’lerinin kaynastigi bir yapidir ve gecis doneminin bir parcasi olarak kabul edilir. 19. Yuzyilin sonu ve 20. Yuzyilin baslarinda gelisen Turkculuk anlayisi isiginda mimarlik sanati ulusal olma yolunda ilerlemistir."],["Bunun sebebi olarak batili yontemlerden uzaklasilmistir. Turkculuk anlayisi, 2. Mesrutiyet’in ilani ile daha da guclenmis ve 1930’lu yillara kadar varligini surdurmustur. Bu anlayis sayesinde batili yontemlerden farkli, milli ve ulusal bir mimari uslup icerisinde eserler verilmistir. Donemlerin degismesi ile birlikte toplumun yeni ihtiyaclari ortaya cikmistir ve bu ihtiyaclari karsilamak adina yeni yapilar yapilmaya baslanmistir. Bu yapilara bankalar, hastaneler, muzeler ornek gosterilebilir."],["Cephe duzenlemeleri Ronesans yapilarina benzeyecek sekilde on cephenin gosterisli olacak sekilde, diger cepheler daha sade kalacak sekilde ayarlanmistir. Dis gorunus konusunda degisimler yasanmasina karsin ic duzenlemeler konusunda pek bir degisim olmamistir. Bunun sebebi donemin getirmis oldugu bir bakis acisi olan, fonksiyonel bir amac gutmeden, mimariyi daha cok bir sanat olarak gormektir."],["Kalin saglicagla."]],"dialogue_index":0,"get_item_indices":[],"give_item_indices":[4],"change_objective_indices":[4],"repeat":false,"print_no_item":true}]},{"marker":[42],"components":[{"dialogues":[["Klasik bati muzigine olan hayranligin artmasi sonucu, Osmanli muzigi bir baskalasim gecirmistir. Bunun arkasindaki en onemli etkenlerden biri de yabanci muzik ustatlarinin Osmanli’da verdigi konserlerdir. Buna ornek olarak Franz Lizst’in Istanbul’da verdigi konserler verilebilir. Biraz enteresan gelebilir ancak o donemlerde Avrupa’da da Turk muziginden alintilar gormek mumkundur. Mozart ve Beethoven’in kullanmis olduklari ritimler ve melodiler mehter muziginin ozelliklerini bunyesinde barindirmaktadirlar."],["Padisahlara eserler hediye edilmesi de sikca gozlenen bir durumdur ve Avrupa muzigi ile kurulan bu yakinlik, bati muzigine olan ilgiyi arttirmis ve iki muzik kulturune de katkilarda bulunmustur."],["Hayirli gunler."]],"dialogue_index":0,"get_item_indices":[],"give_item_indices":[1],"change_objective_indices":[1],"repeat":false,"print_no_item":true}]},{"marker":[43],"components":[{"dialogues":[["19. yuzyil sonlarina dogru Osmanli’da batili sayilabilecek ilk tuval resimleri ortaya cikmistir. Bilindigi uzere Osmanli padisahlari siyasi cokusun onune gecebilmek adina batili teknolojiyi benimsemislerdir. Dogal olarak bu benimseyis bircok alanda degisimlere yol acmistir. Simdi enteresan ve arasinda baglanti olmasi beklenmeyen iki durumdan bahsedecegim. Askeri gucu arttirabilmek adina batili egitimi oncu kabul eden askeri okullar acildi. Acilan bu askeri okullarda da resim dersi mevcuttu."],["Bu ders ilk baslarda teknik bir ders olarak verilmekteydi. Bunun sonucunda da batiyi ornek alan Turk resimleri ortaya cikmaya basladi. Zaman icinde teknik olan bu ders sanatsal bir deger de kazanmaya basladi. Batidaki tekniklerin ogrenimi daha ileri bir seviyeye tasimak amaciyla, bu teknikleri yerinde ogrenmeleri icin Avrupa’ya ogrenci gruplari gonderilmistir. Ilk grup 1829’da gonderilmis, devami 1834, 1835, 1846 seklinde devam etmistir. Gidilen Avrupa ulkeleri ise Ingiltere, Fransa ve Avusturya olmustur."],["Ileriki senelerde, sanat egitimini Avrupa’da almalari icin de ogrenci gonderimi devam etmistir. Bu sekilde egitim goren ve Turk resmine buyuk katkilari bulunan ressamlara Halil Pasa, Sami Yetik, Ibrahim Calli verilebilir. 1883 yilinda Sanayi-i Nefise Mekteb-i Alisi adinda bir guzel sanatlar akademisi kurulmus ve resim egitimini akademik bir disiplin ile yurutecek bir birim olusturulmustur. Asker ressamlar arasinda ogretmen-ogrenci iliskileri kurulmustur. Her kusak kendilerinden once gelenlerin biraktiklari mirasa eklemeler yaparak eser vermeye devam etmislerdir."],["Iyi gunler dilerim."]],"dialogue_index":0,"get_item_indices":[],"give_item_indices":[2],"change_objective_indices":[2],"repeat":false,"print_no_item":true}]},{"marker":[44],"components":[{"dialogues":[["Heykel uretimi Osmanli topraklarina 19.yuzyilin sonlarina dogru varmistir. Bunun en buyuk sebebi, toplumun geleneksel degerlerinden uzaklasmak istememesidir. 1871 yilinda, Sultan Abdulaziz’in Avrupa kentlerine yapmis oldugu gezi donusunde kendi heykelini yaptirmistir ve bu olay heykel sanatinin kesin olarak Osmanli sanatinin bir parcasi haline gelmesini saglamistir. 1883 yilinda Sanayi-i Nefise Mekteb-i Alisi’nin acilmasinin ardindan Osmanli’da heykeltiras yetistirecek bir okul ilk kez acilmis olur."],["Simdi izninle Yervant Osgan Efendi’yi yad etmek istiyorum. Kendisi Avrupa’da heykel uzerine ogrenim goren ilk Osmanli genci olmasi ile bilinir. Sanayi-i Nefise’de 32 yil boyunca ogretim uyesi olarak calisir, bircok sanatcinin yetismesinde rol oynar. Ayni zamanda kendisi de gercekci yorumlarini kattigi bir suru heykel uretmistir."],["Gorusmek uzere."]],"dialogue_index":0,"get_item_indices":[],"give_item_indices":[1],"change_objective_indices":[1],"repeat":false,"print_no_item":true}]},{"marker":[45],"components":[{"dialogues":[["Merhaba"]],"dialogue_index":0,"get_item_indices":[],"give_item_indices":[],"change_objective_indices":[],"repeat":false,"print_no_item":true}]},{"marker":[46],"components":[{"dialogues":[["Selamlar"]],"dialogue_index":0,"get_item_indices":[],"give_item_indices":[],"change_objective_indices":[],"repeat":false,"print_no_item":true}]},{"marker":[47],"components":[{"dialogues":[["HAV HAV"]],"dialogue_index":0,"get_item_indices":[],"give_item_indices":[],"change_objective_indices":[],"repeat":false,"print_no_item":true}]},{"marker":[48],"components":[{"dialogues":[["Hav"]],"dialogue_index":0,"get_item_indices":[],"give_item_indices":[],"change_objective_indices":[],"repeat":false,"print_no_item":true}]},{"marker":[49],"components":[{"dialogues":[["Hav Hav"]],"dialogue_index":0,"get_item_indices":[],"give_item_indices":[],"change_objective_indices":[],"repeat":false,"print_no_item":true}]},{"marker":[50],"components":[{"dialogues":[["Mrrnav"]],"dialogue_index":0,"get_item_indices":[],"give_item_indices":[],"change_objective_indices":[],"repeat":false,"print_no_item":true}]},{"marker":[51],"components":[{"dialogues":[["Miav"]],"dialogue_index":0,"get_item_indices":[],"give_item_indices":[],"change_objective_indices":[],"repeat":false,"print_no_item":true}]},{"marker":[52],"components":[null]}][{"marker":[0],"components":[null]},{"marker":[1],"components":[null]},{"marker":[2],"components":[null]},{"marker":[3],"components":[null]},{"marker":[4],"components":[null]},{"marker":[5],"components":[null]},{"marker":[6],"components":[null]},{"marker":[7],"components":[null]},{"marker":[8],"components":[null]},{"marker":[9],"components":[{"x":24,"y":9}]},{"marker":[10],"components":[null]},{"marker":[11],"components":[null]},{"marker":[12],"components":[null]},{"marker":[13],"components":[null]},{"marker":[14],"components":[null]},{"marker":[15],"components":[null]},{"marker":[16],"components":[{"x":23,"y":19}]},{"marker":[17],"components":[null]},{"marker":[18],"components":[null]},{"marker":[19],"components":[null]},{"marker":[20],"components":[null]},{"marker":[21],"components":[null]},{"marker":[22],"components":[null]},{"marker":[23],"components":[null]},{"marker":[24],"components":[null]},{"marker":[25],"components":[null]},{"marker":[26],"components":[null]},{"marker":[27],"components":[null]},{"marker":[28],"components":[null]},{"marker":[29],"components":[null]},{"marker":[30],"components":[null]},{"marker":[31],"components":[null]},{"marker":[32],"components":[null]},{"marker":[33],"components":[null]},{"marker":[34],"components":[null]},{"marker":[35],"components":[null]},{"marker":[36],"components":[null]},{"marker":[37],"components":[null]},{"marker":[38],"components":[null]},{"marker":[39],"components":[null]},{"marker":[40],"components":[null]},{"marker":[41],"components":[null]},{"marker":[42],"components":[null]},{"marker":[43],"components":[null]},{"marker":[44],"components":[null]},{"marker":[45],"components":[null]},{"marker":[46],"components":[null]},{"marker":[47],"components":[null]},{"marker":[48],"components":[null]},{"marker":[49],"components":[null]},{"marker":[50],"components":[null]},{"marker":[51],"components":[null]},{"marker":[52],"components":[null]}][{"marker":[0],"components":[null]},{"marker":[1],"components":[null]},{"marker":[2],"components":[null]},{"marker":[3],"components":[null]},{"marker":[4],"components":[null]},{"marker":[5],"components":[null]},{"marker":[6],"components":[null]},{"marker":[7],"components":[null]},{"marker":[8],"components":[null]},{"marker":[9],"components":[{"x_end_points":[22,26],"y_end_points":[9,11],"revealer_item":"SecretGateKey","before_reveal":"Wall"}]},{"marker":[10],"components":[null]},{"marker":[11],"components":[null]},{"marker":[12],"components":[null]},{"marker":[13],"components":[null]},{"marker":[14],"components":[null]},{"marker":[15],"components":[null]},{"marker":[16],"components":[{"x_end_points":[16,34],"y_end_points":[10,29],"revealer_item":"OttomanKeyMain","before_reveal":"Floor"}]},{"marker":[17],"components":[null]},{"marker":[18],"components":[null]},{"marker":[19],"components":[null]},{"marker":[20],"components":[null]},{"marker":[21],"components":[null]},{"marker":[22],"components":[null]},{"marker":[23],"components":[null]},{"marker":[24],"components":[null]},{"marker":[25],"components":[null]},{"marker":[26],"components":[null]},{"marker":[27],"components":[null]},{"marker":[28],"components":[null]},{"marker":[29],"components":[null]},{"marker":[30],"components":[null]},{"marker":[31],"components":[null]},{"marker":[32],"components":[null]},{"marker":[33],"components":[null]},{"marker":[34],"components":[null]},{"marker":[35],"components":[null]},{"marker":[36],"components":[null]},{"marker":[37],"components":[null]},{"marker":[38],"components":[null]},{"marker":[39],"components":[null]},{"marker":[40],"components":[null]},{"marker":[41],"components":[null]},{"marker":[42],"components":[null]},{"marker":[43],"components":[null]},{"marker":[44],"components":[null]},{"marker":[45],"components":[null]},{"marker":[46],"components":[null]},{"marker":[47],"components":[null]},{"marker":[48],"components":[null]},{"marker":[49],"components":[null]},{"marker":[50],"components":[null]},{"marker":[51],"components":[null]},{"marker":[52],"components":[null]}][{"marker":[0],"components":[null]},{"marker":[1],"components":[null]},{"marker":[2],"components":[null]},{"marker":[3],"components":[null]},{"marker":[4],"components":[null]},{"marker":[5],"components":[null]},{"marker":[6],"components":[null]},{"marker":[7],"components":[null]},{"marker":[8],"components":[null]},{"marker":[9],"components":[null]},{"marker":[10],"components":[null]},{"marker":[11],"components":[null]},{"marker":[12],"components":[null]},{"marker":[13],"components":[null]},{"marker":[14],"components":[null]},{"marker":[15],"components":[null]},{"marker":[16],"components":[null]},{"marker":[17],"components":[null]},{"marker":[18],"components":[null]},{"marker":[19],"components":[null]},{"marker":[20],"components":[null]},{"marker":[21],"components":[null]},{"marker":[22],"components":[null]},{"marker":[23],"components":[null]},{"marker":[24],"components":[null]},{"marker":[25],"components":[null]},{"marker":[26],"components":[null]},{"marker":[27],"components":[null]},{"marker":[28],"components":[null]},{"marker":[29],"components":[null]},{"marker":[30],"components":[null]},{"marker":[31],"components":[null]},{"marker":[32],"components":[null]},{"marker":[33],"components":[null]},{"marker":[34],"components":[null]},{"marker":[35],"components":[null]},{"marker":[36],"components":[null]},{"marker":[37],"components":[null]},{"marker":[38],"components":[null]},{"marker":[39],"components":[null]},{"marker":[40],"components":[null]},{"marker":[41],"components":[null]},{"marker":[42],"components":[null]},{"marker":[43],"components":[null]},{"marker":[44],"components":[null]},{"marker":[45],"components":[null]},{"marker":[46],"components":[null]},{"marker":[47],"components":[null]},{"marker":[48],"components":[null]},{"marker":[49],"components":[null]},{"marker":[50],"components":[null]},{"marker":[51],"components":[null]},{"marker":[52],"components":[null]}]